amazed/__init__.py
amazed/data_types.py
amazed/maze.py
amazed/builder/AldousBroder.py
amazed/builder/BinaryTree.py
amazed/builder/Builder.py
amazed/builder/DepthFirstSearch.py
amazed/builder/GANModel.py
amazed/builder/GeneticAlgorithm.py
amazed/builder/HuntAndKill.py
amazed/builder/MazeBitmap.py
amazed/builder/RandomCarving.py
amazed/builder/RandomKruskal.py
amazed/builder/RandomPrim.py
amazed/builder/RecursiveDivision.py
amazed/builder/Sidewinder.py
amazed/builder/Spiral.py
amazed/builder/WallsCellularAutomata.py
amazed/builder/__init__.py
amazed/solver/AStar.py
amazed/solver/DFS.py
amazed/solver/DFSHeuristic.py
amazed/solver/DFSRandom.py
amazed/solver/Lee.py
amazed/solver/Solver.py
amazed/solver/__init__.py
amazed/solver/flood_fill.py
amazed/solver/metrics.py
amazed-1.0.2.dist-info/LICENSE
amazed-1.0.2.dist-info/METADATA
amazed-1.0.2.dist-info/WHEEL
amazed-1.0.2.dist-info/top_level.txt
amazed-1.0.2.dist-info/RECORD
