Metadata-Version: 2.1
Name: amazed
Version: 1.0.2
Summary: amazed is a package meant for maze generation & solving.
Home-page: https://github.com/adipeterca/amazed
Author: Peterca Adrian
Author-email: adipeterca@gmail.com
Classifier: Programming Language :: Python :: 3
Classifier: License :: OSI Approved :: MIT License
Classifier: Operating System :: OS Independent
License-File: LICENSE
Requires-Dist: numpy
